onest_captcha/__init__.py
1stcaptcha-1.0.6.dist-info/METADATA
1stcaptcha-1.0.6.dist-info/WHEEL
1stcaptcha-1.0.6.dist-info/RECORD
