Metadata-Version: 2.1
Name: 1stcaptcha
Version: 1.0.6
Summary: Solver recaptchaV2, recaptchaV3, hcaptcha, funcaptcha, imageToText, Zalo Captcha,.... Super fast and cheapest
Home-page: https://github.com/1stcaptcha/1stcaptcha-python
License: MIT
Keywords: 1stcaptcha,recaptcha,recaptchav3,hcaptcha,funcaptcha,imagetotext,zalo captcha,solver captcha
Author: NguyenLinhUET
Author-email: nguyenlinh.uet@gmail.com
Requires-Python: >=3.7,<4.0
Classifier: License :: OSI Approved :: MIT License
Classifier: Programming Language :: Python :: 3
Classifier: Programming Language :: Python :: 3.7
Classifier: Programming Language :: Python :: 3.8
Classifier: Programming Language :: Python :: 3.9
Classifier: Programming Language :: Python :: 3.10
Classifier: Programming Language :: Python :: 3.11
Requires-Dist: requests (>=2.31.0,<3.0.0)
Project-URL: Repository, https://github.com/1stcaptcha/1stcaptcha-python
